{
"month": 11,
"year": 2015,
"presence": [
{
"id": 1,
"startDate": "2015-12-17T06:21:00.000Z",
"endDate": "2015-12-17T15:17:00.000Z",
"type": "Normal",
"comment": null
},
{
"id": 2,
"startDate": "2015-12-18T06:00:00.000Z",
"endDate": "2015-12-18T15:04:00.000Z",
"type": "Normal",
"comment": null
},
{
"id": 3,
"startDate": "2015-12-19T06:00:00.000Z",
"endDate": "2015-12-19T15:00:00.000Z",
"type": "Vacation",
"comment": null
},
{
"id": 4,
"startDate": "2015-12-20T18:01:00.000Z",
"endDate": "2015-12-21T05:52:00.000Z",
"type": "Normal",
"comment": "Double night shift"
},
{
"id": 5,
"startDate": "2015-12-21T06:00:00.000Z",
"endDate": "2015-12-21T15:00:00.000Z",
"type": "Normal",
"comment": null
},
{
"id": 6,
"startDate": "2015-12-22T06:00:00.000Z",
"endDate": "2015-12-22T15:00:00.000Z",
"type": "Normal",
"comment": null
},
{
"id": 7,
"startDate": "2015-12-23T06:00:00.000Z",
"endDate": "2015-12-23T15:00:00.000Z",
"type": "Offsite",
"comment": null
}
]
}